limen/__init__.py
limen/access/__init__.py
limen/access/checker.py
limen/access/friendship.py
limen/access/inheritance.py
limen/core/__init__.py
limen/core/context.py
limen/core/enums.py
limen/core/protocols.py
limen/core/value_objects.py
limen/decorators/__init__.py
limen/decorators/access_decorators.py
limen/decorators/base.py
limen/decorators/friend_decorator.py
limen/descriptors/__init__.py
limen/descriptors/base.py
limen/descriptors/class_method.py
limen/descriptors/factory.py
limen/descriptors/method.py
limen/descriptors/property.py
limen/descriptors/static_method.py
limen/exceptions/__init__.py
limen/exceptions/limen_errors.py
limen/exceptions/message_generators.py
limen/exceptions/method_utils.py
limen/inspection/__init__.py
limen/inspection/stack_inspector.py
limen/system/__init__.py
limen/system/access_control.py
limen/system/event_emitter.py
limen/system/management.py
limen/utils/__init__.py
limen/utils/debug.py
limen/utils/descriptor_utils.py
limen/utils/descriptors.py
limen/utils/error_messages.py
limen/utils/friend_registration.py
limen/utils/implicit.py
limen/utils/introspection.py
limen/utils/naming.py
limen/utils/validation.py
pylimen-1.1.0.dist-info/licenses/LICENSE
pylimen-1.1.0.dist-info/METADATA
pylimen-1.1.0.dist-info/WHEEL
pylimen-1.1.0.dist-info/top_level.txt
pylimen-1.1.0.dist-info/RECORD
